MANIFEST.in
setup.cfg
setup.py
django_realme.egg-info/PKG-INFO
django_realme.egg-info/SOURCES.txt
django_realme.egg-info/dependency_links.txt
django_realme.egg-info/requires.txt
django_realme.egg-info/top_level.txt
realme/__init__.py
realme/app_settings.py
realme/backends.py
realme/bundles.py
realme/tests.py
realme/urls.py
realme/utils.py
realme/views.py
realme/management/__init__.py
realme/management/commands/__init__.py
realme/management/commands/render_metadata.py
realme/samples/authentication_token_period_expired.xml
realme/samples/authn_request.xml
realme/samples/authn_request_url.txt
realme/samples/logon_attributes_token_formatted.xml
realme/samples/logon_attributes_token_raw.xml
realme/samples/opaque_token_escaped_java.xml
realme/samples/opaque_token_raw.xml
realme/samples/opaque_token_request_signed.xml
realme/samples/opaque_token_request_unsigned.xml
realme/samples/opaque_token_response.xml
realme/static/realme/fakeme.css
realme/static/realme/submit.js
realme/templates/realme/error.html
realme/templates/realme/fake-login.html
realme/templates/realme/metadata.xml
realme/templates/realme/opaque_token_request_tmpl.xml
realme/templates/realme/seamless.html