Metadata-Version: 1.1
Name: django-realme
Version: 1.0
Summary: A Django app client for the RealMe service
Home-page: https://github.com/catalyst/django-realme
Author: Catalyst IT
Author-email: UNKNOWN
License: GPL
Download-URL: https://github.com/catalyst/django-realme/archive/1.0.tar.gz
Platform: UNKNOWN
Classifier: Environment :: Web Environment
Classifier: Framework :: Django
Classifier: Intended Audience :: Developers
Classifier: Operating System :: OS Independent
Classifier: Programming Language :: Python
Classifier: Programming Language :: Python :: 3
Classifier: Programming Language :: Python :: 3.4
Classifier: Programming Language :: Python :: 3.5
Classifier: Programming Language :: Python :: 3.6
Classifier: Topic :: Internet :: WWW/HTTP
Classifier: Topic :: Internet :: WWW/HTTP :: Dynamic Content
